jupytutor/__init__.py
jupytutor/_version.py
jupytutor/handlers.py
jupytutor/labextension/package.json
jupytutor/labextension/static/237.fd7acad62cc218608a2d.js
jupytutor/labextension/static/312.773d93d591cc8c4a6cc9.js
jupytutor/labextension/static/392.8a6b607136ab033258e9.js
jupytutor/labextension/static/392.8a6b607136ab033258e9.js.LICENSE.txt
jupytutor/labextension/static/772.d11ebfddc127515acc55.js
jupytutor/labextension/static/remoteEntry.b9e1157c823a84c3029e.js
jupytutor/labextension/static/style.js
jupytutor/labextension/static/third-party-licenses.json
jupytutor-0.1.3.data/data/etc/jupyter/jupyter_server_config.d/jupytutor.json
jupytutor-0.1.3.data/data/share/jupyter/labextensions/jupytutor/package.json
jupytutor-0.1.3.data/data/share/jupyter/labextensions/jupytutor/static/237.fd7acad62cc218608a2d.js
jupytutor-0.1.3.data/data/share/jupyter/labextensions/jupytutor/static/312.773d93d591cc8c4a6cc9.js
jupytutor-0.1.3.data/data/share/jupyter/labextensions/jupytutor/static/392.8a6b607136ab033258e9.js
jupytutor-0.1.3.data/data/share/jupyter/labextensions/jupytutor/static/392.8a6b607136ab033258e9.js.LICENSE.txt
jupytutor-0.1.3.data/data/share/jupyter/labextensions/jupytutor/static/772.d11ebfddc127515acc55.js
jupytutor-0.1.3.data/data/share/jupyter/labextensions/jupytutor/static/remoteEntry.b9e1157c823a84c3029e.js
jupytutor-0.1.3.data/data/share/jupyter/labextensions/jupytutor/static/style.js
jupytutor-0.1.3.data/data/share/jupyter/labextensions/jupytutor/static/third-party-licenses.json
jupytutor-0.1.3.data/data/share/jupyter/labextensions/jupytutor/install.json
jupytutor-0.1.3.dist-info/METADATA
jupytutor-0.1.3.dist-info/WHEEL
jupytutor-0.1.3.dist-info/licenses/LICENSE
jupytutor-0.1.3.dist-info/RECORD
