Metadata-Version: 2.4
Name: jupytutor
Version: 0.1.3
Summary: A Jupyter extension for providing students LLM feedback based on autograder results and supplied course context.
Project-URL: Homepage, https://github.com/kevyg03/jupytutor
Project-URL: Bug Tracker, https://github.com/kevyg03/jupytutor/issues
Project-URL: Repository, https://github.com/kevyg03/jupytutor.git
Author-email: Kevin Gillespie <kevin.gillespie@berkeley.edu>
License: BSD 3-Clause License
License-File: LICENSE
Keywords: jupyter,jupyterlab,jupyterlab-extension
Classifier: Framework :: Jupyter
Classifier: Framework :: Jupyter :: JupyterLab
Classifier: Framework :: Jupyter :: JupyterLab :: 4
Classifier: Framework :: Jupyter :: JupyterLab :: Extensions
Classifier: Framework :: Jupyter :: JupyterLab :: Extensions :: Prebuilt
Classifier: License :: OSI Approved :: BSD License
Classifier: Programming Language :: Python
Classifier: Programming Language :: Python :: 3
Classifier: Programming Language :: Python :: 3.9
Classifier: Programming Language :: Python :: 3.10
Classifier: Programming Language :: Python :: 3.11
Classifier: Programming Language :: Python :: 3.12
Classifier: Programming Language :: Python :: 3.13
Requires-Python: >=3.9
Requires-Dist: jupyter-server<3,>=2.0.0
